odoo10_addon_web_timeline-10.0.1.2.1-py2.7-nspkg.pth
odoo/addons/web_timeline/README.rst
odoo/addons/web_timeline/__init__.py
odoo/addons/web_timeline/__manifest__.py
odoo/addons/web_timeline/i18n/es.po
odoo/addons/web_timeline/i18n/fr.po
odoo/addons/web_timeline/i18n/hr.po
odoo/addons/web_timeline/i18n/nl_NL.po
odoo/addons/web_timeline/models/__init__.py
odoo/addons/web_timeline/models/ir_view.py
odoo/addons/web_timeline/static/description/icon.png
odoo/addons/web_timeline/static/lib/vis/vis-timeline-graph2d.min.css
odoo/addons/web_timeline/static/lib/vis/vis-timeline-graph2d.min.js
odoo/addons/web_timeline/static/src/css/web_timeline.css
odoo/addons/web_timeline/static/src/js/web_timeline.js
odoo/addons/web_timeline/static/src/xml/web_timeline.xml
odoo/addons/web_timeline/views/web_timeline.xml
odoo10_addon_web_timeline-10.0.1.2.1.dist-info/DESCRIPTION.rst
odoo10_addon_web_timeline-10.0.1.2.1.dist-info/METADATA
odoo10_addon_web_timeline-10.0.1.2.1.dist-info/RECORD
odoo10_addon_web_timeline-10.0.1.2.1.dist-info/WHEEL
odoo10_addon_web_timeline-10.0.1.2.1.dist-info/metadata.json
odoo10_addon_web_timeline-10.0.1.2.1.dist-info/namespace_packages.txt
odoo10_addon_web_timeline-10.0.1.2.1.dist-info/top_level.txt
